sarunas_k_mod1_atsiskaitymas/__init__.py
sarunas_k_mod1_atsiskaitymas/web_read.py
Sarunas_K_mod1_atsiskaitymas-0.3.dist-info/METADATA
Sarunas_K_mod1_atsiskaitymas-0.3.dist-info/WHEEL
Sarunas_K_mod1_atsiskaitymas-0.3.dist-info/top_level.txt
Sarunas_K_mod1_atsiskaitymas-0.3.dist-info/RECORD
